Metadata-Version: 2.4
Name: pretix-paystack
Version: 1.0.2
Summary: Accept payments through Paystack with M-Pesa support - a modern payment provider for Africa.
Author-email: Joakim Bwire <joakimbwire23@gmail.com>
Maintainer-email: Joakim Bwire <joakimbwire23@gmail.com>
License-Expression: Apache-2.0
Project-URL: homepage, https://github.com/MYHEAT-Choose-Life/pretix-paystack
Project-URL: repository, https://github.com/MYHEAT-Choose-Life/pretix-paystack
Keywords: pretix,paystack,mpesa,payments,africa,kenya,mobile-money
Classifier: Development Status :: 5 - Production/Stable
Classifier: Intended Audience :: Developers
Classifier: Intended Audience :: Other Audience
Classifier: Programming Language :: Python :: 3
Classifier: Programming Language :: Python :: 3.8
Classifier: Programming Language :: Python :: 3.9
Classifier: Programming Language :: Python :: 3.10
Classifier: Programming Language :: Python :: 3.11
Classifier: Topic :: Internet :: WWW/HTTP
Classifier: Topic :: Office/Business :: Financial :: Point-Of-Sale
Classifier: Topic :: Software Development :: Libraries :: Python Modules
Requires-Python: >=3.8
License-File: LICENSE
Requires-Dist: requests>=2.25.0
Requires-Dist: cryptography>=3.4.0
Dynamic: license-file
